pyopn/__init__.py
pyopn/client.py
pyopn/utils.py
pyopn/controllers/__init__.py
pyopn/controllers/activity.py
pyopn/controllers/cpu_usage.py
pyopn/controllers/interface.py
pyopn/controllers/system.py
pyopn/modules/__init__.py
pyopn/modules/diagnostics.py
python_opn-0.2.0.dist-info/licenses/LICENSE
python_opn-0.2.0.dist-info/METADATA
python_opn-0.2.0.dist-info/WHEEL
python_opn-0.2.0.dist-info/top_level.txt
python_opn-0.2.0.dist-info/RECORD
