Metadata-Version: 2.4
Name: python-opn
Version: 0.2.0
Summary: A comprehensive OPNSense API client
Author-email: Jay Deiman <admin@splitstreams.com>
License:                     GNU GENERAL PUBLIC LICENSE
Project-URL: homepage, https://github.com/crustymonkey/py-opn
Project-URL: issues, https://github.com/crustymonkey/py-opn/issues
Classifier: Programming Language :: Python :: 3
Classifier: Operating System :: OS Independent
Classifier: Development Status :: 4 - Beta
Requires-Python: >=3.9
License-File: LICENSE
Dynamic: license-file
